LICENSE.txt
README.md
setup.cfg
setup.py
pycron/__init__.py
python_cron.egg-info/PKG-INFO
python_cron.egg-info/SOURCES.txt
python_cron.egg-info/dependency_links.txt
python_cron.egg-info/requires.txt
python_cron.egg-info/top_level.txt