Metadata-Version: 2.1
Name: python-cron
Version: 1.0.0
Summary: A simple Python library providing cron functionality via the use of a single decorator.
Home-page: https://github.com/whdev1/pycron
Author: whdev1
Author-email: whdev1@protonmail.com
License: MIT
Download-URL: https://github.com/whdev1/pycron/archive/refs/tags/v1.0.0.tar.gz
Keywords: pycron,cron,timed functions,automation
Platform: UNKNOWN
Classifier: Development Status :: 3 - Alpha
Classifier: Intended Audience :: Developers
Classifier: Topic :: Software Development :: Build Tools
Classifier: License :: OSI Approved :: MIT License
Classifier: Programming Language :: Python :: 3.9
Classifier: Programming Language :: Python :: 3.10
License-File: LICENSE.txt
